src/critical_component_finder_rv/__init__.py
src/critical_component_finder_rv/main.py
critical_component_finder_rv-1.1.0.dist-info/LICENSE
critical_component_finder_rv-1.1.0.dist-info/METADATA
critical_component_finder_rv-1.1.0.dist-info/WHEEL
critical_component_finder_rv-1.1.0.dist-info/top_level.txt
critical_component_finder_rv-1.1.0.dist-info/RECORD
